PyStageLinQ/DataClasses.py
PyStageLinQ/Device.py
PyStageLinQ/EngineServices.py
PyStageLinQ/ErrorCodes.py
PyStageLinQ/MessageClasses.py
PyStageLinQ/Network.py
PyStageLinQ/PyStageLinQ.py
PyStageLinQ/Token.py
PyStageLinQ/__init__.py
pystagelinq-0.2.1.dist-info/METADATA
pystagelinq-0.2.1.dist-info/WHEEL
pystagelinq-0.2.1.dist-info/licenses/LICENSE
pystagelinq-0.2.1.dist-info/RECORD
