Metadata-Version: 2.3
Name: PyStageLinQ
Version: 0.2.1
Summary: A Python implementation of a StagelinQ protocol
Project-URL: Homepage, https://github.com/Jaxc/PyStageLinQ
Project-URL: Bug Tracker, https://github.com/Jaxc/PyStageLinQ/issues
Project-URL: Documentation, https://pystagelinq.readthedocs.io/en/latest/
Project-URL: Funding, https://ko-fi.com/jaxcie
Author-email: jaxc@skrooter.com
License-File: LICENSE
Keywords: DJ,Denon DJ,Prime Go,StageLinQ,Streaming,VJ
Classifier: Development Status :: 4 - Beta
Classifier: Intended Audience :: Developers
Classifier: License :: OSI Approved :: MIT License
Classifier: Programming Language :: Python :: 3.10
Classifier: Topic :: Multimedia :: Sound/Audio
Requires-Python: >=3.10
Provides-Extra: docs
Requires-Dist: myst-parser; extra == 'docs'
Requires-Dist: sphinx; extra == 'docs'
